nwscapparser3/__init__.py
nwscapparser3/nws_cap_parser.py
nwscapparser3/us_states.py
nwscapparser3/xml2obj.py
nwscapparser3-3.0.6.data/data/LICENSE
nwscapparser3-3.0.6.data/data/cap.2020-05-07T14_12_00.xml
nwscapparser3-3.0.6.data/data/demo.py
nwscapparser3-3.0.6.data/data/readme.rst
nwscapparser3-3.0.6.dist-info/LICENSE
nwscapparser3-3.0.6.dist-info/METADATA
nwscapparser3-3.0.6.dist-info/WHEEL
nwscapparser3-3.0.6.dist-info/top_level.txt
nwscapparser3-3.0.6.dist-info/RECORD
