Metadata-Version: 2.1
Name: nwscapparser3
Version: 3.0.6
Summary: NWS CAP Parser for Python3
Home-page: https://github.com/GrantGMiller/NWS-CAP-parser
Author: Grant Miller. Based on the work of Robert Morris (robert@emthree.com)
Author-email: grant@grant-miller.com
License: PSF
Keywords: python3 cap common alert protocol grant miller robert morris xml
Platform: UNKNOWN
Requires-Dist: requests
Requires-Dist: lxml
